pwlfit/__init__.py
pwlfit/driver.py
pwlfit/fit.py
pwlfit/grid.py
pwlfit/region.py
pwlfit/util.py
pwlfit/data/__init__.py
pwlfit/data/sampleA.json
pwlfit/data/sampleB.json
pwlfit/data/sampleC.json
pwlfit-0.2.0.dist-info/licenses/LICENSE
pwlfit-0.2.0.dist-info/METADATA
pwlfit-0.2.0.dist-info/WHEEL
pwlfit-0.2.0.dist-info/top_level.txt
pwlfit-0.2.0.dist-info/RECORD
