Metadata-Version: 2.4
Name: pwlfit
Version: 0.2.0
Summary: Package for piecewise linear fitting of noisy data
Home-page: https://github.com/dkirkby/pwlfit
Author: David Kirkby
Author-email: dkirkby@uci.edu
Project-URL: Documentation, https://github.com/dkirkby/pwlfit
Project-URL: Bug Reports, https://github.com/dkirkby/pwlfit/issues
Project-URL: Source Code, https://github.com/dkirkby/pwlfit
Keywords: linear fitting,piecewise linear,astronomy,data analysis
Classifier: Development Status :: 4 - Beta
Classifier: Intended Audience :: Science/Research
Classifier: Topic :: Scientific/Engineering :: Astronomy
Classifier: Programming Language :: Python :: 3
Classifier: Programming Language :: Python :: 3 :: Only
Classifier: Operating System :: OS Independent
Requires-Python: >=3.8
License-File: LICENSE
Requires-Dist: numpy
Requires-Dist: scipy
Requires-Dist: pyyaml
Provides-Extra: dev
Requires-Dist: check-manifest; extra == "dev"
Dynamic: author
Dynamic: author-email
Dynamic: classifier
Dynamic: description
Dynamic: description-content-type
Dynamic: home-page
Dynamic: keywords
Dynamic: license-file
Dynamic: project-url
Dynamic: provides-extra
Dynamic: requires-dist
Dynamic: requires-python
Dynamic: summary
